{
  "settings": {},
  "dependencies": [
    "10FB27DD3C7BEC2F"
  ],
  "tasks": {
    "6690451CCAB62CA1": {
      "type": "heracles:item",
      "item": "gtceu:inductor"
    }
  },
  "rewards": {},
  "display": {
    "title": "Inductors",
    "description": [
      "<subtitle id=\"3DFFA8F91452C62A\" bold=\"true\" centered=\"true\" color=\"lightgray\"/>",
      "<hr/>",
      "<task task=\"6690451CCAB62CA1\" quest=\"3DFFA8F91452C62A\"/>",
      "<hr/>",
      "A Circuit Component that you can now make thanks to the &&3MV Assembler&&r.",
      "<br/>",
      "If you want the cheapest recipe, &&aNickel-Zinc Ferrite&&r is the way to go."
    ],
    "icon": {
      "type": "heracles:item",
      "item": "gtceu:inductor"
    },
    "subtitle": {
      "text": "Z = jwL"
    },
    "groups": {
      "§bMV§r - Medium Voltage": {
        "position": [
          324,
          -60
        ]
      }
    }
  }
}